pirogue_admin_client/__init__.py
pirogue_admin_client/adapters.py
pirogue_admin_client/cli.py
pirogue_admin_client/types.py
pirogue_admin_client-2.0.4.dist-info/licenses/LICENSE
pirogue_admin_client-2.0.4.dist-info/METADATA
pirogue_admin_client-2.0.4.dist-info/WHEEL
pirogue_admin_client-2.0.4.dist-info/entry_points.txt
pirogue_admin_client-2.0.4.dist-info/top_level.txt
pirogue_admin_client-2.0.4.dist-info/RECORD
