Metadata-Version: 2.4
Name: pirogue-admin-client
Version: 2.0.4
Summary: Administration client for the PiRogue
Author-email: Christophe Andral <christophe@andral.fr>
Maintainer-email: U+039b <hello@pts-project.org>
License-Expression: GPL-3.0+
Project-URL: repository, https://github.com/PiRogueToolSuite/pirogue-admin
Project-URL: issues, https://github.com/PiRogueToolSuite/pirogue-admin/issues
Requires-Python: >=3.9
License-File: LICENSE
Requires-Dist: cryptography~=38.0.4
Requires-Dist: grpcio
Requires-Dist: pirogue_admin_api==2.0.2
Requires-Dist: pyyaml
Dynamic: license-file
